{
  "mode": "paper_demo",
  "event_slug": "btc-updown-5m-1782060300",
  "question": "Bitcoin Up or Down - June 21, 12:45PM-12:50PM ET",
  "seconds_to_close": 382.2017,
  "btc_price": 64026.515,
  "polymarket": {
    "yes": 0.51,
    "no": 0.48,
    "volume_24h": 35.685486
  },
  "model": {
    "loaded": true,
    "tradeable": false,
    "block_reason": "auc < 0.54",
    "metrics": {
      "n_train": 9624,
      "n_test": 2401,
      "accuracy": 0.5022907122032486,
      "auc": 0.5254353695531884,
      "auc_raw": 0.5254353695531884,
      "flip": false,
      "brier": 0.2523423622414016,
      "logloss": 0.697886478433012,
      "base_rate": 0.4581255195344971,
      "brier_lgbm": 0.25349208509226934,
      "brier_xgb": 0.2544149477893616,
      "brier_lstm": 0.3446516253055638,
      "tradeable": false,
      "trade_block_reason": "auc < 0.54"
    }
  },
  "primary": {
    "action": "skip",
    "source": "ml",
    "side": null,
    "price": null,
    "edge": null,
    "p_up": null,
    "confidence": null,
    "required_edge": null,
    "quality_score": 0.0,
    "size_pct": 0.0,
    "reasons": [
      "model_not_tradeable: auc < 0.54"
    ],
    "details": {},
    "should_open": false
  },
  "shadow": {
    "action": "skip",
    "source": "shadow_baseline",
    "side": null,
    "price": null,
    "edge": 0.013207100919938396,
    "p_up": null,
    "confidence": null,
    "required_edge": null,
    "quality_score": 0.0,
    "size_pct": 0.0,
    "reasons": [
      "baseline not aligned mom=+0.00020 imb=-0.161"
    ],
    "details": {
      "momentum": 0.00020401115636185593,
      "imbalance": -0.16106395534619522
    },
    "should_open": false
  },
  "thresholds": {
    "min_trade_edge": 0.08,
    "min_model_confidence": 0.1,
    "min_decision_quality": 55.0,
    "shadow_min_edge": 0.005,
    "shadow_min_confidence": 0.005
  },
  "updated_at": "2026-06-21T16:43:37.809368+00:00"
}