{
  "mode": "paper_demo",
  "event_slug": "btc-updown-5m-1781309100",
  "question": "Bitcoin Up or Down - June 12, 8:05PM-8:10PM ET",
  "seconds_to_close": 321.370106,
  "btc_price": 63554.965,
  "polymarket": {
    "yes": 0.47,
    "no": 0.52,
    "volume_24h": 1.960783
  },
  "model": {
    "loaded": true,
    "tradeable": false,
    "block_reason": "brier > 0.245",
    "metrics": {
      "n_train": 8220,
      "n_test": 2049,
      "accuracy": 0.5446559297218155,
      "auc": 0.5525405731040307,
      "auc_raw": 0.5525405731040307,
      "flip": false,
      "brier": 0.24718145141646145,
      "logloss": 0.6874438137637349,
      "base_rate": 0.45608272506082725,
      "brier_lgbm": 0.2504679906229678,
      "brier_xgb": 0.2475603314186657,
      "brier_lstm": 0.3483384994123707,
      "tradeable": false,
      "trade_block_reason": "brier > 0.245"
    }
  },
  "primary": {
    "action": "skip",
    "source": "ml",
    "side": null,
    "price": null,
    "edge": null,
    "p_up": null,
    "confidence": null,
    "required_edge": null,
    "quality_score": 0.0,
    "size_pct": 0.0,
    "reasons": [
      "model_not_tradeable: brier > 0.245"
    ],
    "details": {},
    "should_open": false
  },
  "shadow": {
    "action": "skip",
    "source": "shadow_baseline",
    "side": null,
    "price": null,
    "edge": 0.026764215286478127,
    "p_up": null,
    "confidence": null,
    "required_edge": null,
    "quality_score": 0.0,
    "size_pct": 0.0,
    "reasons": [
      "baseline not aligned mom=+0.00016 imb=-0.775"
    ],
    "details": {
      "momentum": 0.00016433701113481363,
      "imbalance": -0.7747619914164604
    },
    "should_open": false
  },
  "thresholds": {
    "min_trade_edge": 0.08,
    "min_model_confidence": 0.1,
    "min_decision_quality": 55.0,
    "shadow_min_edge": 0.005,
    "shadow_min_confidence": 0.005
  },
  "updated_at": "2026-06-13T00:04:38.651125+00:00"
}