{
  "mode": "paper_demo",
  "event_slug": "btc-updown-5m-1778712300",
  "question": "Bitcoin Up or Down - May 13, 6:45PM-6:50PM ET",
  "seconds_to_close": 549.306796,
  "btc_price": 79303.435,
  "polymarket": {
    "yes": 0.51,
    "no": 0.48,
    "volume_24h": 402.25215299999996
  },
  "model": {
    "loaded": true,
    "tradeable": false,
    "block_reason": "auc < 0.54",
    "metrics": {
      "n_train": 2717,
      "n_test": 674,
      "accuracy": 0.5059347181008902,
      "auc": 0.5166111932938855,
      "auc_raw": 0.5166111932938855,
      "flip": false,
      "brier": 0.25106965642021867,
      "logloss": 0.6952681216190747,
      "base_rate": 0.4541774015458226,
      "brier_lgbm": 0.25257184126964277,
      "brier_xgb": 0.25106965642021867,
      "brier_lstm": 0.35941619843498296,
      "tradeable": false,
      "trade_block_reason": "auc < 0.54"
    }
  },
  "primary": {
    "action": "skip",
    "source": "ml",
    "side": null,
    "price": null,
    "edge": null,
    "p_up": null,
    "confidence": null,
    "required_edge": null,
    "quality_score": 0.0,
    "size_pct": 0.0,
    "reasons": [
      "model_not_tradeable: auc < 0.54"
    ],
    "details": {},
    "should_open": false
  },
  "shadow": {
    "action": "open",
    "source": "shadow_baseline",
    "side": "NO",
    "price": 0.48,
    "edge": 0.026587545945086808,
    "p_up": null,
    "confidence": 0.2216614114718019,
    "required_edge": 0.005,
    "quality_score": 91.57,
    "size_pct": 0.0,
    "reasons": [],
    "details": {
      "momentum": -0.00022107023989533073,
      "imbalance": -0.6655754059918769
    },
    "should_open": true
  },
  "thresholds": {
    "min_trade_edge": 0.08,
    "min_model_confidence": 0.1,
    "min_decision_quality": 55.0,
    "shadow_min_edge": 0.005,
    "shadow_min_confidence": 0.005
  },
  "updated_at": "2026-05-13T22:40:50.703836+00:00"
}